panpdf/__init__.py
panpdf/main.py
panpdf/py.typed
panpdf/tools.py
panpdf/filters/__init__.py
panpdf/filters/attribute.py
panpdf/filters/cell.py
panpdf/filters/crossref.py
panpdf/filters/filter.py
panpdf/filters/jupyter.py
panpdf/filters/layout.py
panpdf/filters/snippet.py
panpdf/filters/verbatim.py
panpdf/filters/zotero.py
panpdf-0.7.2.dist-info/METADATA
panpdf-0.7.2.dist-info/WHEEL
panpdf-0.7.2.dist-info/entry_points.txt
panpdf-0.7.2.dist-info/licenses/LICENSE
panpdf-0.7.2.dist-info/RECORD
