Metadata-Version: 2.4
Name: panpdf
Version: 0.7.2
Summary: Transform Jupyter Notebooks and Markdown into publication-quality PDF documents with high-fidelity visualizations.
Project-URL: Documentation, https://daizutabi.github.io/panpdf
Project-URL: Source, https://github.com/daizutabi/panpdf
Project-URL: Issues, https://github.com/daizutabi/panpdf/issues
Author-email: daizutabi <daizutabi@gmail.com>
License: MIT License
License-File: LICENSE
Keywords: academic,document,jupyter,latex,markdown,notebook,pandoc,pdf,pgf,publication,research,scientific,visualization
Classifier: Development Status :: 4 - Beta
Classifier: Intended Audience :: Education
Classifier: Intended Audience :: Science/Research
Classifier: License :: OSI Approved :: MIT License
Classifier: Operating System :: OS Independent
Classifier: Programming Language :: Python
Classifier: Programming Language :: Python :: 3.10
Classifier: Programming Language :: Python :: 3.11
Classifier: Programming Language :: Python :: 3.12
Classifier: Programming Language :: Python :: 3.13
Classifier: Topic :: Documentation
Classifier: Topic :: Scientific/Engineering
Classifier: Topic :: Software Development :: Documentation
Classifier: Topic :: Text Processing :: Markup
Requires-Python: >=3.10
Requires-Dist: aiohttp>=3
Requires-Dist: nbstore>=0.4.1
Requires-Dist: panflute>=2.3.1
Requires-Dist: pyyaml>=6
Requires-Dist: pyzotero>=1.6
Requires-Dist: rich>=13
Requires-Dist: typer>=0.15
